runtime/__init__.py
runtime/cli.py
runtime/runtime.py
runtime/data/ai_written_features.run
runtime/data/code_is_text.run
runtime/data/dynamic_variables.run
runtime/data/hot_swapping_built_ins.run
runtime_lang-0.1.6.dist-info/licenses/LICENSE
runtime_lang-0.1.6.dist-info/METADATA
runtime_lang-0.1.6.dist-info/WHEEL
runtime_lang-0.1.6.dist-info/entry_points.txt
runtime_lang-0.1.6.dist-info/top_level.txt
runtime_lang-0.1.6.dist-info/RECORD
