Metadata-Version: 2.4
Name: runtime_lang
Version: 0.1.6
Summary: Interpreter for the RUNTIME programming language
License-File: LICENSE
Requires-Dist: colorama
Requires-Dist: platformdirs
Requires-Dist: requests
Dynamic: description
Dynamic: description-content-type
Dynamic: license-file
Dynamic: requires-dist
Dynamic: summary
